ssl_framework/__init__.py
ssl_framework/byol.py
ssl_framework/simclr.py
ssl_framework-0.2.4.dist-info/LICENSE
ssl_framework-0.2.4.dist-info/METADATA
ssl_framework-0.2.4.dist-info/WHEEL
ssl_framework-0.2.4.dist-info/top_level.txt
ssl_framework-0.2.4.dist-info/RECORD
